llama_index/storage/docstore/mongodb/__init__.py
llama_index/storage/docstore/mongodb/base.py
llama_index_storage_docstore_mongodb-0.4.0.dist-info/METADATA
llama_index_storage_docstore_mongodb-0.4.0.dist-info/WHEEL
llama_index_storage_docstore_mongodb-0.4.0.dist-info/licenses/LICENSE
llama_index_storage_docstore_mongodb-0.4.0.dist-info/RECORD
