Metadata-Version: 2.4
Name: llama-index-storage-docstore-mongodb
Version: 0.4.0
Summary: llama-index docstore mongodb integration
Author-email: Your Name <you@example.com>
License-Expression: MIT
License-File: LICENSE
Requires-Python: <4.0,>=3.9
Requires-Dist: llama-index-core<0.14,>=0.13.0
Requires-Dist: llama-index-storage-kvstore-mongodb<0.5,>=0.4.0
